client/__init__.py
client/all_voice_lab.py
client/model.py
client/__pycache__/__init__.cpython-311.pyc
client/__pycache__/all_voice_lab.cpython-311.pyc
client/__pycache__/audio_isolation.cpython-311.pyc
client/__pycache__/get_all_voices.cpython-311.pyc
client/__pycache__/get_supported_voice_model.cpython-311.pyc
client/__pycache__/model.cpython-311.pyc
client/__pycache__/speech_to_speech.cpython-311.pyc
client/__pycache__/text_to_speech.cpython-311.pyc
my_mcp_casper/__init__.py
my_mcp_casper/server.py
my_mcp_casper/server_v2.py
my_mcp_casper/utils.py
my_mcp_casper/tools/__init__.py
my_mcp_casper/tools/base.py
my_mcp_casper/tools/dubbing.py
my_mcp_casper/tools/speech.py
my_mcp_casper/tools/utils.py
my_mcp_casper/tools/voice_info.py
my_mcp_casper-0.0.15.dist-info/METADATA
my_mcp_casper-0.0.15.dist-info/WHEEL
my_mcp_casper-0.0.15.dist-info/entry_points.txt
my_mcp_casper-0.0.15.dist-info/top_level.txt
my_mcp_casper-0.0.15.dist-info/RECORD
