Metadata-Version: 2.4
Name: my-mcp-casper
Version: 0.0.15
Summary: My MCP Server
Author-email: My <support@example.com>
Keywords: mcp,text-to-speech,speech-to-text,voice-cloning
Requires-Python: >=3.11
Requires-Dist: mcp[cli]>=1.6.0
Requires-Dist: requests>=2.32.3
Requires-Dist: setuptools>=45
